Workbook
Name SegmentaciónDeDatos_Categoria: #N/A
Name SegmentaciónDeDatos_Fecha_Operacion: #N/A
Name SegmentaciónDeDatos_Region: #N/A

Sheet Dashboard Final
B2: REPORTE EJECUTIVO DE VENTAS Y MÁRGENES
B3: Dashboard interactivo de monitoreo comercial y desempeño regional
B5: VENTAS TOTALES | E5: TICKET PROMEDIO | H5: CUMPLIMIENTO DE META
B6: =GETPIVOTDATA("Precio_Unitario",Dashboard!$A$3) -> 8647405 | E6: =GETPIVOTDATA("Promedio de Precio_Unitario2",Dashboard!$A$3) -> 432370.25 | H6: =GETPIVOTDATA("Precio_Unitario",Dashboard!$A$3)/50000000 -> 0.1729481

Sheet Hechos_Transacciones
A1: ID_Transaccion | B1: Fecha_Operacion | C1: ID_Cliente_Ref | D1: SKU_Codigo_Ref | E1: Cantidad | F1: Precio_Unitario | G1: Categoria | H1: Region
A2: TX-100000 | B2: 46324 | C2: CLI-001 | D2: TECN-01 | E2: 7 | F2: 401778 | G2: =_xlfn.XLOOKUP(D2,Productos!A:A,Productos!C:C,"Sin categoria") -> Electrónica | H2: =_xlfn.XLOOKUP(C2,Clientes!A:A,Clientes!C:C,"Sin Region") -> Cali
A3: TX-100001 | B3: 46217 | C3: CLI-002 | D3: ELEC-02 | E3: 1 | F3: 810179 | G3: =_xlfn.XLOOKUP(D3,Productos!A:A,Productos!C:C,"Sin categoria") -> Electrónica | H3: =_xlfn.XLOOKUP(C3,Clientes!A:A,Clientes!C:C,"Sin Region") -> Bogotá
A4: TX-100002 | B4: 46063 | C4: CLI-003 | D4: TECN-01 | E4: 4 | F4: 783797 | G4: =_xlfn.XLOOKUP(D4,Productos!A:A,Productos!C:C,"Sin categoria") -> Electrónica | H4: =_xlfn.XLOOKUP(C4,Clientes!A:A,Clientes!C:C,"Sin Region") -> Bogotá
A5: TX-100003 | B5: 46142 | C5: CLI-004 | D5: ELEC-02 | E5: 6 | F5: 215555 | G5: =_xlfn.XLOOKUP(D5,Productos!A:A,Productos!C:C,"Sin categoria") -> Electrónica | H5: =_xlfn.XLOOKUP(C5,Clientes!A:A,Clientes!C:C,"Sin Region") -> Bogotá
A6: TX-100004 | B6: 46354 | C6: CLI-005 | D6: ELEC-02 | E6: 4 | F6: 216339 | G6: =_xlfn.XLOOKUP(D6,Productos!A:A,Productos!C:C,"Sin categoria") -> Electrónica | H6: =_xlfn.XLOOKUP(C6,Clientes!A:A,Clientes!C:C,"Sin Region") -> Cali
A7: TX-100005 | B7: 46375 | C7: CLI-006 | D7: LBLA-02 | E7: 4 | F7: 78659 | G7: =_xlfn.XLOOKUP(D7,Productos!A:A,Productos!C:C,"Sin categoria") -> Electrónica | H7: =_xlfn.XLOOKUP(C7,Clientes!A:A,Clientes!C:C,"Sin Region") -> Cali
A8: TX-100006 | B8: 46313 | C8: CLI-007 | D8: TECN-02 | E8: 11 | F8: 526141 | G8: =_xlfn.XLOOKUP(D8,Productos!A:A,Productos!C:C,"Sin categoria") -> Electrónica | H8: =_xlfn.XLOOKUP(C8,Clientes!A:A,Clientes!C:C,"Sin Region") -> Barranquilla
A9: TX-100007 | B9: 46322 | C9: CLI-008 | D9: HOGA-01 | E9: 3 | F9: 579277 | G9: =_xlfn.XLOOKUP(D9,Productos!A:A,Productos!C:C,"Sin categoria") -> Hogar | H9: =_xlfn.XLOOKUP(C9,Clientes!A:A,Clientes!C:C,"Sin Region") -> Bogotá
A10: TX-100008 | B10: 46104 | C10: CLI-009 | D10: HOGA-01 | E10: 8 | F10: 599816 | G10: =_xlfn.XLOOKUP(D10,Productos!A:A,Productos!C:C,"Sin categoria") -> Hogar | H10: =_xlfn.XLOOKUP(C10,Clientes!A:A,Clientes!C:C,"Sin Region") -> Medellín
A11: TX-100009 | B11: 46371 | C11: CLI-010 | D11: ELEC-02 | E11: 6 | F11: 161970 | G11: =_xlfn.XLOOKUP(D11,Productos!A:A,Productos!C:C,"Sin categoria") -> Electrónica | H11: =_xlfn.XLOOKUP(C11,Clientes!A:A,Clientes!C:C,"Sin Region") -> Bogotá
A12: TX-100010 | B12: 46157 | C12: CLI-011 | D12: LBLA-01 | E12: 5 | F12: 714987 | G12: =_xlfn.XLOOKUP(D12,Productos!A:A,Productos!C:C,"Sin categoria") -> Linea blanca | H12: =_xlfn.XLOOKUP(C12,Clientes!A:A,Clientes!C:C,"Sin Region") -> Bogotá
A13: TX-100011 | B13: 46294 | C13: CLI-012 | D13: ELEC-01 | E13: 6 | F13: 367451 | G13: =_xlfn.XLOOKUP(D13,Productos!A:A,Productos!C:C,"Sin categoria") -> Electrónica | H13: =_xlfn.XLOOKUP(C13,Clientes!A:A,Clientes!C:C,"Sin Region") -> Medellín
... A101: TX-100099 | B101: 46368 | C101: CLI-100 | D101: HOGA-01 | E101: 1 | F101: 322304 | G101: =_xlfn.XLOOKUP(D101,Productos!A:A,Productos!C:C,"Sin categoria") -> Hogar | H101: =_xlfn.XLOOKUP(C101,Clientes!A:A,Clientes!C:C,"Sin Region") -> Barranquilla

Sheet Dashboard
A3: Etiquetas de fila | B3: Suma de Precio_Unitario | C3: Promedio de Precio_Unitario2 | D3: Etiquetas de fila | E3: Suma de Precio_Unitario | G3: Ventas Brutas | H3: =B9 -> 8647405
A4: Barranquilla | B4: 1316147 | C4: 438715.67 | D4: Hogar | E4: 8647405 | G4: Descuentos Comercial | H4: -3500000
A5: Bogotá | B5: 4414688 | C5: 441468.8 | D5: Total general | E5: 8647405 | G5: Costo de Ventas | H5: -18000000
A6: Cali | B6: 374164 | C6: 374164 | G6: Gastos Logísticos | H6: -4200000
A7: Cartagena | B7: 752390 | C7: 376195 | G7: Margen Neto Final | H7: =SUM(H3:H6) -> -17052595
A8: Medellín | B8: 1790016 | C8: 447504
A9: Total general | B9: 8647405 | C9: 432370.25
A15: Etiquetas de fila | B15: Suma de Precio_Unitario
A16: ene | B16: 838188
A17: feb | B17: 458038
A18: mar | B18: 599816
A19: may | B19: 127804
A20: jul | B20: 702365
A21: ago | B21: 1334898
A22: sep | B22: 848013
A23: oct | B23: 1108140
A24: nov | B24: 1303918
A25: dic | B25: 1326225
A26: Total general | B26: 8647405

Sheet Clientes
A1: ID_Cliente_Clave | B1: Nombre_RazonSocial | C1: Region_Geografica
A2: CLI-001 | B2: Juan Pérez | C2: Cali
A3: CLI-002 | B3: María Rodríguez | C3: Bogotá
A4: CLI-003 | B4: Carlos Gómez | C4: Bogotá
A5: CLI-004 | B5: Ana Martínez | C5: Bogotá
A6: CLI-005 | B6: Luis Fernández | C6: Cali
A7: CLI-006 | B7: Andrés Ramírez | C7: Cali
A8: CLI-007 | B8: Sofía Hernández | C8: Barranquilla
A9: CLI-008 | B9: Diego Torres | C9: Bogotá
A10: CLI-009 | B10: Laura Castro | C10: Medellín
A11: CLI-010 | B11: Miguel Rojas | C11: Bogotá
A12: CLI-011 | B12: Natalia Morales | C12: Bogotá
... A101: CLI-100 | B101: Óscar Velasco | C101: Barranquilla

Sheet Productos
A1: SKU_Clave | B1: Producto_Descripcion | C1: Categoria_Agrupador
A2: ELEC-01 | B2: TV Smart 55 | C2: Electrónica
A3: ELEC-02 | B3: Microondas 20L | C3: Electrónica
A4: LBLA-01 | B4: Lavarropas Automático | C4: Linea blanca
A5: LBLA-02 | B5: Heladera No Frost | C5: Electrónica
A6: TECN-01 | B6: Celular Smartphone | C6: Electrónica
A7: TECN-02 | B7: Notebook Pro | C7: Electrónica
A8: HOGA-01 | B8: Cafetera Express | C8: Hogar
A9: HOGA-02 | B9: Aspiradora Robot | C9: Hogar

Sheet Calculos
C3: ID_Transaccion | D3: Fecha_Operacion | E3: ID_Cliente_Ref | F3: SKU_Codigo_Ref | G3: Cantidad | H3: Precio_Unitario | I3: Total | J3: Comisión | L3: Prompt para ChatGPT | P3: Mes | Q3: Total_Mensual
C4: TX-100000 | D4: 46324 | E4: CLI-001 | F4: TECN-01 | G4: 7 | H4: 401778 | I4: =Tabla13[[#This Row],[Cantidad]]*Tabla13[[#This Row],[Precio_Unitario]] -> 2812446 | J4: =IF(AND(I4>3000000,G4>=5),I4*0.06,IF(I4>1000000,I4*0.04,I4*0.02)) -> 112497.84 | L4: Contexto: Tengo una tabla de ventas en Excel con las columnas Cantidad (G) y Total (I) por cada transacción. Objetivo: Necesito una fórmula que calcule una comisión escalonada: 6% si el Total es mayor a 3.000.000 y la Cantidad es mayor o igual a 5; 4% si el Total es mayor a 1.000.000; y 2% en cualquier otro caso. Ejemplo: Si Total=3.500.000 y Cantidad=6, la comisión debería ser 210.000 (6%). Si Total=1.500.000 y Cantidad=2, la comisión debería ser 60.000 (4%). Formato: Damee solo la fórmula de Excel en español, usando SI, Y, anidados, sin explicaciones adicionales. | P4: 46023 | Q4: =SUMIFS($I$4:$I$103,$D$4:$D$103,">="&P4,$D$4:$D$103,"<"&EDATE(P4,1)) -> 29282604
C5: TX-100001 | D5: 46217 | E5: CLI-002 | F5: ELEC-02 | G5: 1 | H5: 810179 | I5: =Tabla13[[#This Row],[Cantidad]]*Tabla13[[#This Row],[Precio_Unitario]] -> 810179 | J5: =IF(AND(I5>3000000,G5>=5),I5*0.06,IF(I5>1000000,I5*0.04,I5*0.02)) -> 16203.58 | P5: =EDATE(P4,1) -> 46054 | Q5: =SUMIFS($I$4:$I$103,$D$4:$D$103,">="&P5,$D$4:$D$103,"<"&EDATE(P5,1)) -> 16709861
C6: TX-100002 | D6: 46063 | E6: CLI-003 | F6: TECN-01 | G6: 4 | H6: 783797 | I6: =Tabla13[[#This Row],[Cantidad]]*Tabla13[[#This Row],[Precio_Unitario]] -> 3135188 | J6: =IF(AND(I6>3000000,G6>=5),I6*0.06,IF(I6>1000000,I6*0.04,I6*0.02)) -> 125407.52 | P6: =EDATE(P5,1) -> 46082 | Q6: =SUMIFS($I$4:$I$103,$D$4:$D$103,">="&P6,$D$4:$D$103,"<"&EDATE(P6,1)) -> 13354869
C7: TX-100003 | D7: 46142 | E7: CLI-004 | F7: ELEC-02 | G7: 6 | H7: 215555 | I7: =Tabla13[[#This Row],[Cantidad]]*Tabla13[[#This Row],[Precio_Unitario]] -> 1293330 | J7: =IF(AND(I7>3000000,G7>=5),I7*0.06,IF(I7>1000000,I7*0.04,I7*0.02)) -> 51733.2 | P7: =EDATE(P6,1) -> 46113 | Q7: =SUMIFS($I$4:$I$103,$D$4:$D$103,">="&P7,$D$4:$D$103,"<"&EDATE(P7,1)) -> 21947424
C8: TX-100004 | D8: 46354 | E8: CLI-005 | F8: ELEC-02 | G8: 4 | H8: 216339 | I8: =Tabla13[[#This Row],[Cantidad]]*Tabla13[[#This Row],[Precio_Unitario]] -> 865356 | J8: =IF(AND(I8>3000000,G8>=5),I8*0.06,IF(I8>1000000,I8*0.04,I8*0.02)) -> 17307.12 | P8: =EDATE(P7,1) -> 46143 | Q8: =SUMIFS($I$4:$I$103,$D$4:$D$103,">="&P8,$D$4:$D$103,"<"&EDATE(P8,1)) -> 21195597
C9: TX-100005 | D9: 46375 | E9: CLI-006 | F9: LBLA-02 | G9: 4 | H9: 78659 | I9: =Tabla13[[#This Row],[Cantidad]]*Tabla13[[#This Row],[Precio_Unitario]] -> 314636 | J9: =IF(AND(I9>3000000,G9>=5),I9*0.06,IF(I9>1000000,I9*0.04,I9*0.02)) -> 6292.72 | P9: =EDATE(P8,1) -> 46174 | Q9: =SUMIFS($I$4:$I$103,$D$4:$D$103,">="&P9,$D$4:$D$103,"<"&EDATE(P9,1)) -> 20347776
C10: TX-100006 | D10: 46313 | E10: CLI-007 | F10: TECN-02 | G10: 11 | H10: 526141 | I10: =Tabla13[[#This Row],[Cantidad]]*Tabla13[[#This Row],[Precio_Unitario]] -> 5787551 | J10: =IF(AND(I10>3000000,G10>=5),I10*0.06,IF(I10>1000000,I10*0.04,I10*0.02)) -> 347253.06 | P10: =EDATE(P9,1) -> 46204 | Q10: =SUMIFS($I$4:$I$103,$D$4:$D$103,">="&P10,$D$4:$D$103,"<"&EDATE(P10,1)) -> 9593996
C11: TX-100007 | D11: 46322 | E11: CLI-008 | F11: HOGA-01 | G11: 3 | H11: 579277 | I11: =Tabla13[[#This Row],[Cantidad]]*Tabla13[[#This Row],[Precio_Unitario]] -> 1737831 | J11: =IF(AND(I11>3000000,G11>=5),I11*0.06,IF(I11>1000000,I11*0.04,I11*0.02)) -> 69513.24 | P11: =EDATE(P10,1) -> 46235 | Q11: =SUMIFS($I$4:$I$103,$D$4:$D$103,">="&P11,$D$4:$D$103,"<"&EDATE(P11,1)) -> 47002364
C12: TX-100008 | D12: 46104 | E12: CLI-009 | F12: HOGA-01 | G12: 8 | H12: 599816 | I12: =Tabla13[[#This Row],[Cantidad]]*Tabla13[[#This Row],[Precio_Unitario]] -> 4798528 | J12: =IF(AND(I12>3000000,G12>=5),I12*0.06,IF(I12>1000000,I12*0.04,I12*0.02)) -> 287911.68 | L12: Formula | P12: =EDATE(P11,1) -> 46266 | Q12: =SUMIFS($I$4:$I$103,$D$4:$D$103,">="&P12,$D$4:$D$103,"<"&EDATE(P12,1)) -> 17428362
C13: TX-100009 | D13: 46371 | E13: CLI-010 | F13: ELEC-02 | G13: 6 | H13: 161970 | I13: =Tabla13[[#This Row],[Cantidad]]*Tabla13[[#This Row],[Precio_Unitario]] -> 971820 | J13: =IF(AND(I13>3000000,G13>=5),I13*0.06,IF(I13>1000000,I13*0.04,I13*0.02)) -> 19436.4 | L13: "=SI(Y(I4>3000000;G4>=5);I4*0,06;SI(I4>1000000;I4*0,04;I4*0,02))" | P13: =EDATE(P12,1) -> 46296 | Q13: =SUMIFS($I$4:$I$103,$D$4:$D$103,">="&P13,$D$4:$D$103,"<"&EDATE(P13,1)) -> 24804003
C14: TX-100010 | D14: 46157 | E14: CLI-011 | F14: LBLA-01 | G14: 5 | H14: 714987 | I14: =Tabla13[[#This Row],[Cantidad]]*Tabla13[[#This Row],[Precio_Unitario]] -> 3574935 | J14: =IF(AND(I14>3000000,G14>=5),I14*0.06,IF(I14>1000000,I14*0.04,I14*0.02)) -> 214496.1 | P14: =EDATE(P13,1) -> 46327 | Q14: =SUMIFS($I$4:$I$103,$D$4:$D$103,">="&P14,$D$4:$D$103,"<"&EDATE(P14,1)) -> 19503917
C15: TX-100011 | D15: 46294 | E15: CLI-012 | F15: ELEC-01 | G15: 6 | H15: 367451 | I15: =Tabla13[[#This Row],[Cantidad]]*Tabla13[[#This Row],[Precio_Unitario]] -> 2204706 | J15: =IF(AND(I15>3000000,G15>=5),I15*0.06,IF(I15>1000000,I15*0.04,I15*0.02)) -> 88188.24 | P15: =EDATE(P14,1) -> 46357 | Q15: =SUMIFS($I$4:$I$103,$D$4:$D$103,">="&P15,$D$4:$D$103,"<"&EDATE(P15,1)) -> 21019233
C16: TX-100012 | D16: 46271 | E16: CLI-013 | F16: ELEC-02 | G16: 8 | H16: 621510 | I16: =Tabla13[[#This Row],[Cantidad]]*Tabla13[[#This Row],[Precio_Unitario]] -> 4972080 | J16: =IF(AND(I16>3000000,G16>=5),I16*0.06,IF(I16>1000000,I16*0.04,I16*0.02)) -> 298324.8
C17: TX-100013 | D17: 46299 | E17: CLI-014 | F17: LBLA-02 | G17: 6 | H17: 504381 | I17: =Tabla13[[#This Row],[Cantidad]]*Tabla13[[#This Row],[Precio_Unitario]] -> 3026286 | J17: =IF(AND(I17>3000000,G17>=5),I17*0.06,IF(I17>1000000,I17*0.04,I17*0.02)) -> 181577.16
C18: TX-100014 | D18: 46055 | E18: CLI-015 | F18: TECN-02 | G18: 4 | H18: 52540 | I18: =Tabla13[[#This Row],[Cantidad]]*Tabla13[[#This Row],[Precio_Unitario]] -> 210160 | J18: =IF(AND(I18>3000000,G18>=5),I18*0.06,IF(I18>1000000,I18*0.04,I18*0.02)) -> 4203.2
C19: TX-100015 | D19: 46192 | E19: CLI-016 | F19: ELEC-02 | G19: 4 | H19: 610427 | I19: =Tabla13[[#This Row],[Cantidad]]*Tabla13[[#This Row],[Precio_Unitario]] -> 2441708 | J19: =IF(AND(I19>3000000,G19>=5),I19*0.06,IF(I19>1000000,I19*0.04,I19*0.02)) -> 97668.32
C20: TX-100016 | D20: 46265 | E20: CLI-017 | F20: HOGA-01 | G20: 6 | H20: 489154 | I20: =Tabla13[[#This Row],[Cantidad]]*Tabla13[[#This Row],[Precio_Unitario]] -> 2934924 | J20: =IF(AND(I20>3000000,G20>=5),I20*0.06,IF(I20>1000000,I20*0.04,I20*0.02)) -> 117396.96
C21: TX-100017 | D21: 46353 | E21: CLI-018 | F21: ELEC-02 | G21: 2 | H21: 305735 | I21: =Tabla13[[#This Row],[Cantidad]]*Tabla13[[#This Row],[Precio_Unitario]] -> 611470 | J21: =IF(AND(I21>3000000,G21>=5),I21*0.06,IF(I21>1000000,I21*0.04,I21*0.02)) -> 12229.4
C22: TX-100018 | D22: 46259 | E22: CLI-019 | F22: LBLA-02 | G22: 9 | H22: 147664 | I22: =Tabla13[[#This Row],[Cantidad]]*Tabla13[[#This Row],[Precio_Unitario]] -> 1328976 | J22: =IF(AND(I22>3000000,G22>=5),I22*0.06,IF(I22>1000000,I22*0.04,I22*0.02)) -> 53159.04
C23: TX-100019 | D23: 46144 | E23: CLI-020 | F23: LBLA-01 | G23: 7 | H23: 106483 | I23: =Tabla13[[#This Row],[Cantidad]]*Tabla13[[#This Row],[Precio_Unitario]] -> 745381 | J23: =IF(AND(I23>3000000,G23>=5),I23*0.06,IF(I23>1000000,I23*0.04,I23*0.02)) -> 14907.62
C24: TX-100020 | D24: 46255 | E24: CLI-021 | F24: TECN-01 | G24: 9 | H24: 739022 | I24: =Tabla13[[#This Row],[Cantidad]]*Tabla13[[#This Row],[Precio_Unitario]] -> 6651198 | J24: =IF(AND(I24>3000000,G24>=5),I24*0.06,IF(I24>1000000,I24*0.04,I24*0.02)) -> 399071.88
C25: TX-100021 | D25: 46052 | E25: CLI-022 | F25: ELEC-01 | G25: 9 | H25: 601926 | I25: =Tabla13[[#This Row],[Cantidad]]*Tabla13[[#This Row],[Precio_Unitario]] -> 5417334 | J25: =IF(AND(I25>3000000,G25>=5),I25*0.06,IF(I25>1000000,I25*0.04,I25*0.02)) -> 325040.04
C26: TX-100022 | D26: 46327 | E26: CLI-023 | F26: ELEC-02 | G26: 10 | H26: 303175 | I26: =Tabla13[[#This Row],[Cantidad]]*Tabla13[[#This Row],[Precio_Unitario]] -> 3031750 | J26: =IF(AND(I26>3000000,G26>=5),I26*0.06,IF(I26>1000000,I26*0.04,I26*0.02)) -> 181905
C27: TX-100023 | D27: 46312 | E27: CLI-024 | F27: TECN-02 | G27: 4 | H27: 323517 | I27: =Tabla13[[#This Row],[Cantidad]]*Tabla13[[#This Row],[Precio_Unitario]] -> 1294068 | J27: =IF(AND(I27>3000000,G27>=5),I27*0.06,IF(I27>1000000,I27*0.04,I27*0.02)) -> 51762.72
... C103: TX-100099 | D103: 46368 | E103: CLI-100 | F103: HOGA-01 | G103: 1 | H103: 322304 | I103: =Tabla13[[#This Row],[Cantidad]]*Tabla13[[#This Row],[Precio_Unitario]] -> 322304 | J103: =IF(AND(I103>3000000,G103>=5),I103*0.06,IF(I103>1000000,I103*0.04,I103*0.02)) -> 6446.08

Sheet Previsión
A1: Mes | B1: Total_Mensual | C1: Previsión(Total_Mensual) | D1: Intervalo de confianza(Total_Mensual) | E1: Límite_Inferior | F1: Límite_Superior
A2: 46023 | B2: 29282604 | E2: =IF(C2="","",C2-D2) | F2: =IF(C2="","",C2+D2)
A3: 46054 | B3: 16709861 | E3: =IF(C3="","",C3-D3) | F3: =IF(C3="","",C3+D3)
A4: 46082 | B4: 13354869 | E4: =IF(C4="","",C4-D4) | F4: =IF(C4="","",C4+D4)
A5: 46113 | B5: 21947424 | E5: =IF(C5="","",C5-D5) | F5: =IF(C5="","",C5+D5)
A6: 46143 | B6: 21195597 | E6: =IF(C6="","",C6-D6) | F6: =IF(C6="","",C6+D6)
A7: 46174 | B7: 20347776 | E7: =IF(C7="","",C7-D7) | F7: =IF(C7="","",C7+D7)
A8: 46204 | B8: 9593996 | E8: =IF(C8="","",C8-D8) | F8: =IF(C8="","",C8+D8)
A9: 46235 | B9: 47002364 | E9: =IF(C9="","",C9-D9) | F9: =IF(C9="","",C9+D9)
A10: 46266 | B10: 17428362 | E10: =IF(C10="","",C10-D10) | F10: =IF(C10="","",C10+D10)
A11: 46296 | B11: 24804003 | E11: =IF(C11="","",C11-D11) | F11: =IF(C11="","",C11+D11)
A12: 46327 | B12: 19503917 | E12: =IF(C12="","",C12-D12) | F12: =IF(C12="","",C12+D12)
A13: 46357 | B13: 21019233 | E13: =IF(C13="","",C13-D13) | F13: =IF(C13="","",C13+D13)
A14: 46388 | C14: =_xlfn.FORECAST.ETS(A14,$B$2:$B$13,$A$2:$A$13,1,1) -> 24588896 | D14: =_xlfn.FORECAST.ETS.CONFINT(A14,$B$2:$B$13,$A$2:$A$13,0.95,1,1) -> 21062715 | E14: =IF(C14="","",C14-D14) -> 3526181.3 | F14: =IF(C14="","",C14+D14) -> 45651611
A15: 46419 | C15: =_xlfn.FORECAST.ETS(A15,$B$2:$B$13,$A$2:$A$13,1,1) -> 24740017 | D15: =_xlfn.FORECAST.ETS.CONFINT(A15,$B$2:$B$13,$A$2:$A$13,0.95,1,1) -> 21231896 | E15: =IF(C15="","",C15-D15) -> 3508120.8 | F15: =IF(C15="","",C15+D15) -> 45971913
A16: 46447 | C16: =_xlfn.FORECAST.ETS(A16,$B$2:$B$13,$A$2:$A$13,1,1) -> 24891137 | D16: =_xlfn.FORECAST.ETS.CONFINT(A16,$B$2:$B$13,$A$2:$A$13,0.95,1,1) -> 21402382 | E16: =IF(C16="","",C16-D16) -> 3488754.7 | F16: =IF(C16="","",C16+D16) -> 46293519
A17: 46478 | C17: =_xlfn.FORECAST.ETS(A17,$B$2:$B$13,$A$2:$A$13,1,1) -> 25042257 | D17: =_xlfn.FORECAST.ETS.CONFINT(A17,$B$2:$B$13,$A$2:$A$13,0.95,1,1) -> 21574164 | E17: =IF(C17="","",C17-D17) -> 3468093.4 | F17: =IF(C17="","",C17+D17) -> 46616421

Sheet Buscador
A2: ID_Cliente | B2: CLI-005
A3: Nombre: | B3: =_xlfn.XLOOKUP(B2,Clientes!A:A,Clientes!B:B) -> Luis Fernández
A4: Región: | B4: =_xlfn.XLOOKUP(B2,Clientes!A:A,Clientes!C:C) -> Cali

Sheet Justificación
B2: Justificación de decisiones Escogí una comisión escalonada porque refleja mejor cómo funciona un incentivo de ventas real: si el Total de la venta supera $3.000.000 y la Cantidad es de 5 unidades o más, la comisión sube a 6%, ya que premia tanto el monto como el volumen de la venta. Si solo supera $1.000.000, la comisión es del 4%, y en cualquier otro caso queda en 2%. Esto motiva a vender más y en mayor cantidad, no solo montos altos aislados. Para la previsión, usé el histórico mensual de ventas de 2026 (12 meses) y proyecté 4 periodos hacia adelante (enero a abril de 2027), un horizonte razonable dado que solo se cuenta con un año completo de datos. La hoja de previsión de Excel genera las fórmulas de forma dinámica (con PRONOSTICO.ETS), vinculadas directamente a la tabla de origen en Calculos, por lo que se actualiza automáticamente si cambian los datos históricos. El buscador resuelve la necesidad de ubicar rápido la información de un cliente sin tener que revisar manualmente la tabla completa: con el ID_Cliente correspondiente, la función BUSCARX permite obtener de una vez el nombre y la región asociados a ese cliente.

Sheet Reporte_Insights
C24: REGISTRO DE AUDITORÍA Y PROMPTS DE IA (ABOGADO DEL DIABLO)
C26: 1. PROMPT DE AUDITORÍA DE INSIGHTS:
C27: Actúa como un director financiero (CFO) y analista 'abogado del diablo'. Analiza mis conclusiones de ventas: Electrónica representa el 70% de la facturación y Bogotá/Medellín concentran el 63% de los ingresos. ¿Qué sesgos, riesgos de concentración o variables omitidas (ej. costos logísticos, devoluciones, margen neto real) podrían invalidar la idea de que Electrónica es la categoría más rentable?
C33: 2. RESPUESTA Y REFLEXIÓN COGNITIVA DE LA IA:
C35: El análisis identificó un sesgo de volumen vs. rentabilidad. Concentrar el 70% en Electrónica expone al negocio a un alto costo de inventario y obsolescencia. Además, el margen neto real de Electrónica se ve afectado por costos de envío elevados frente a Línea Blanca. Basado en esto, se incorporó el gráfico de Cascada para auditar el margen neto real y no solo la venta bruta.

Sheet Matriz_Ventas
A1: Categoria / Region | B1: Bogotá | C1: Medellín | D1: Cali | E1: Barranquilla | F1: Cartagena
A2: Electrónica | B2: =SUMIFS(Tabla1[Precio_Unitario],Tabla1[Categoria],$A2,Tabla1[Region],B$1) -> 11833679 | C2: =SUMIFS(Tabla1[Precio_Unitario],Tabla1[Categoria],$A2,Tabla1[Region],C$1) -> 6162932 | D2: =SUMIFS(Tabla1[Precio_Unitario],Tabla1[Categoria],$A2,Tabla1[Region],D$1) -> 6701530 | E2: =SUMIFS(Tabla1[Precio_Unitario],Tabla1[Categoria],$A2,Tabla1[Region],E$1) -> 3921336 | F2: =SUMIFS(Tabla1[Precio_Unitario],Tabla1[Categoria],$A2,Tabla1[Region],F$1) -> 1226579
A3: Hogar | B3: =SUMIFS(Tabla1[Precio_Unitario],Tabla1[Categoria],$A3,Tabla1[Region],B$1) -> 4414688 | C3: =SUMIFS(Tabla1[Precio_Unitario],Tabla1[Categoria],$A3,Tabla1[Region],C$1) -> 1790016 | D3: =SUMIFS(Tabla1[Precio_Unitario],Tabla1[Categoria],$A3,Tabla1[Region],D$1) -> 374164 | E3: =SUMIFS(Tabla1[Precio_Unitario],Tabla1[Categoria],$A3,Tabla1[Region],E$1) -> 1316147 | F3: =SUMIFS(Tabla1[Precio_Unitario],Tabla1[Categoria],$A3,Tabla1[Region],F$1) -> 752390
A4: Linea blanca | B4: =SUMIFS(Tabla1[Precio_Unitario],Tabla1[Categoria],$A4,Tabla1[Region],B$1) -> 821470 | C4: =SUMIFS(Tabla1[Precio_Unitario],Tabla1[Categoria],$A4,Tabla1[Region],C$1) -> 1639831 | D4: =SUMIFS(Tabla1[Precio_Unitario],Tabla1[Categoria],$A4,Tabla1[Region],D$1) -> 1221555 | E4: =SUMIFS(Tabla1[Precio_Unitario],Tabla1[Categoria],$A4,Tabla1[Region],E$1) -> 0 | F4: =SUMIFS(Tabla1[Precio_Unitario],Tabla1[Categoria],$A4,Tabla1[Region],F$1) -> 0
A7: Categoria buscada: | B7: Hogar
A8: Region buscada: | B8: Bogotá
A9: Resultado: | B9: =INDEX($B$2:$F$4,MATCH(B7,$A$2:$A$4,0),MATCH(B8,$B$1:$F$1,0)) -> 4414688

Sheet Vencimientos
A1: Feriados_2026 | B1: ID_Transaccion | C1: Fecha_Vencimiento
A2: 46023 | B2: =Hechos_Transacciones!A2 -> TX-100000 | C2: =WORKDAY(Hechos_Transacciones!B2,30,$A$2:$A$13) -> 46370
A3: 46028 | B3: =Hechos_Transacciones!A3 -> TX-100001 | C3: =WORKDAY(Hechos_Transacciones!B3,30,$A$2:$A$13) -> 46261
A4: 46104 | B4: =Hechos_Transacciones!A4 -> TX-100002 | C4: =WORKDAY(Hechos_Transacciones!B4,30,$A$2:$A$13) -> 46106
A5: 46114 | B5: =Hechos_Transacciones!A5 -> TX-100003 | C5: =WORKDAY(Hechos_Transacciones!B5,30,$A$2:$A$13) -> 46188
A6: 46115 | B6: =Hechos_Transacciones!A6 -> TX-100004 | C6: =WORKDAY(Hechos_Transacciones!B6,30,$A$2:$A$13) -> 46400
A7: 46143 | B7: =Hechos_Transacciones!A7 -> TX-100005 | C7: =WORKDAY(Hechos_Transacciones!B7,30,$A$2:$A$13) -> 46419
A8: 46167 | B8: =Hechos_Transacciones!A8 -> TX-100006 | C8: =WORKDAY(Hechos_Transacciones!B8,30,$A$2:$A$13) -> 46353
A9: 46223 | B9: =Hechos_Transacciones!A9 -> TX-100007 | C9: =WORKDAY(Hechos_Transacciones!B9,30,$A$2:$A$13) -> 46366
A10: 46241 | B10: =Hechos_Transacciones!A10 -> TX-100008 | C10: =WORKDAY(Hechos_Transacciones!B10,30,$A$2:$A$13) -> 46149
A11: 46363 | B11: =Hechos_Transacciones!A11 -> TX-100009 | C11: =WORKDAY(Hechos_Transacciones!B11,30,$A$2:$A$13) -> 46414
A12: 46364 | B12: =Hechos_Transacciones!A12 -> TX-100010 | C12: =WORKDAY(Hechos_Transacciones!B12,30,$A$2:$A$13) -> 46202
A13: 46381 | B13: =Hechos_Transacciones!A13 -> TX-100011 | C13: =WORKDAY(Hechos_Transacciones!B13,30,$A$2:$A$13) -> 46336
B14: =Hechos_Transacciones!A14 -> TX-100012 | C14: =WORKDAY(Hechos_Transacciones!B14,30,$A$2:$A$13) -> 46311
B15: =Hechos_Transacciones!A15 -> TX-100013 | C15: =WORKDAY(Hechos_Transacciones!B15,30,$A$2:$A$13) -> 46339
B16: =Hechos_Transacciones!A16 -> TX-100014 | C16: =WORKDAY(Hechos_Transacciones!B16,30,$A$2:$A$13) -> 46097
B17: =Hechos_Transacciones!A17 -> TX-100015 | C17: =WORKDAY(Hechos_Transacciones!B17,30,$A$2:$A$13) -> 46237
B18: =Hechos_Transacciones!A18 -> TX-100016 | C18: =WORKDAY(Hechos_Transacciones!B18,30,$A$2:$A$13) -> 46307
B19: =Hechos_Transacciones!A19 -> TX-100017 | C19: =WORKDAY(Hechos_Transacciones!B19,30,$A$2:$A$13) -> 46400
B20: =Hechos_Transacciones!A20 -> TX-100018 | C20: =WORKDAY(Hechos_Transacciones!B20,30,$A$2:$A$13) -> 46301
B21: =Hechos_Transacciones!A21 -> TX-100019 | C21: =WORKDAY(Hechos_Transacciones!B21,30,$A$2:$A$13) -> 46188
B22: =Hechos_Transacciones!A22 -> TX-100020 | C22: =WORKDAY(Hechos_Transacciones!B22,30,$A$2:$A$13) -> 46297
B23: =Hechos_Transacciones!A23 -> TX-100021 | C23: =WORKDAY(Hechos_Transacciones!B23,30,$A$2:$A$13) -> 46094
B24: =Hechos_Transacciones!A24 -> TX-100022 | C24: =WORKDAY(Hechos_Transacciones!B24,30,$A$2:$A$13) -> 46371
B25: =Hechos_Transacciones!A25 -> TX-100023 | C25: =WORKDAY(Hechos_Transacciones!B25,30,$A$2:$A$13) -> 46353
... B101: =Hechos_Transacciones!A101 -> TX-100099 | C101: =WORKDAY(Hechos_Transacciones!B101,30,$A$2:$A$13) -> 46412

Sheet Auditoria
A1: Mes | B1: Total_Ventas | C1: Num_Mes
A2: Enero | B2: {=SUMPRODUCT((MONTH(Tabla1[Fecha_Operacion])=C2)*(YEAR(Tabla1[Fecha_Operacion])=2026)*Tabla1[Precio_Unitario])} -> 4266240 | C2: 1
A3: Febrero | B3: {=SUMPRODUCT((MONTH(Tabla1[Fecha_Operacion])=C3)*(YEAR(Tabla1[Fecha_Operacion])=2026)*Tabla1[Precio_Unitario])} -> 2894052 | C3: 2
A4: Marzo | B4: {=SUMPRODUCT((MONTH(Tabla1[Fecha_Operacion])=C4)*(YEAR(Tabla1[Fecha_Operacion])=2026)*Tabla1[Precio_Unitario])} -> 2448001 | C4: 3
A5: Abril | B5: {=SUMPRODUCT((MONTH(Tabla1[Fecha_Operacion])=C5)*(YEAR(Tabla1[Fecha_Operacion])=2026)*Tabla1[Precio_Unitario])} -> 2934651 | C5: 4
A7: Total_Anual_Parcial | B7: =SUM(B3:B6) -> 8276704

Sheet Refactor_LET
A1: Formula Original
A2: =IF(AND(Calculos!I4>3000000,Calculos!G4>=5),Calculos!I4*0.06,IF(Calculos!I4>1000000,Calculos!I4*0.04,Calculos!I4*0.02)) -> 112497.84
A4: Formula con LET
A5: =_xlfn.LET(_xlpm.total,Calculos!I4,_xlpm.cantidad,Calculos!G4,IF(AND(_xlpm.total>3000000,_xlpm.cantidad>=5),_xlpm.total*0.06,IF(_xlpm.total>1000000,_xlpm.total*0.04,_xlpm.total*0.02))) -> 112497.84
A7: La fórmula original repite la referencia I4 cuatro veces, dificultando su mantenimiento si cambia la columna del Total. La versión con LET nombra "total" y "cantidad" una sola vez, mejorando la legibilidad y trazabilidad sin alterar el resultado numérico, ambas fórmulas devuelven el mismo valor ($112.498) para el mismo cliente.
